{"cameraMode":{"drawMode":0,"name":"Shaded","section":"Shading Mode"},"sceneLighting":true,"audioPlay":false,"sceneViewState":{"showFog":true,"showMaterialUpdate":false,"showSkybox":true,"showFlares":true,"showImageEffects":true,"showParticleSystems":true},"in2DMode":false,"pivot":{"x":256.4810485839844,"y":584.3025512695313,"z":4.844439506530762},"rotation":{"x":0.0048095304518938068,"y":-0.0015047370688989759,"z":0.000007295998329936992,"w":0.9999873638153076},"size":647.5009765625,"orthographic":false}